asyncio_orvibo/__init__.py
asyncio_orvibo/allone.py
asyncio_orvibo/asyncio_udp.py
asyncio_orvibo/const.py
asyncio_orvibo/orvibo_udp.py
asyncio_orvibo/s20.py
asyncio_orvibo-1.19.dist-info/LICENSE
asyncio_orvibo-1.19.dist-info/METADATA
asyncio_orvibo-1.19.dist-info/WHEEL
asyncio_orvibo-1.19.dist-info/top_level.txt
asyncio_orvibo-1.19.dist-info/RECORD
