Metadata-Version: 2.1
Name: asyncio-orvibo
Version: 1.19
Summary: Asyncio module for Orvibo devices control
Home-page: https://github.com/p3g4asus/asyncio-orvibo
Author: p3g4asus
Author-email: fulminedipegasus@gmail.com
License: UNKNOWN
Platform: UNKNOWN
Classifier: Programming Language :: Python :: 3
Classifier: License :: OSI Approved :: MIT License
Classifier: Operating System :: OS Independent
